[
  {
    "id": "OP01-003",
    "name": "Monkey D. Luffy",
    "type": "Leader",
    "cost": 0,
    "power": 5000,
    "effect": "[Activate Main] Once Per Turn (4 DON!!): Set up to 1 of your Supernovas or Straw Hat Crew type Character cards with a cost of 5 or less as active. It gains +1000 power during this turn.",
    "traits": [
      "Supernovas",
      "Straw Hat Crew"
    ],
    "color": [
      "Red",
      "Green"
    ],
    "attribute": [
      "Strike"
    ],
    "rarity": 1,
    "life": 4,
    "counter": 0,
    "labels": [
      "Buff Power",
      "Low Cost"
    ],
    "archetype": "Midrange"
  },
  {
    "id": "OP01-001",
    "name": "Roronoa Zoro",
    "type": "Leader",
    "cost": 0,
    "power": 5000,
    "effect": "DON!!x1 Your Turn All of your Characters gain +1000 power.",
    "traits": [
      "Supernovas",
      "Straw Hat Crew"
    ],
    "color": [
      "Red"
    ],
    "attribute": [
      "Slash"
    ],
    "rarity": 1,
    "life": 5,
    "counter": 0,
    "labels": [
      "Buff Power",
      "Low Cost"
    ],
    "archetype": "Aggro"
  },
  {
    "id": "OP01-061",
    "name": "Kaido",
    "type": "Leader",
    "cost": 0,
    "power": 5000,
    "effect": "DON!! x1During your turnOnce per turn When one of your opponents Characters is KOd, you can add 1 DON!! card from your DON!! deck and set it as active.",
    "traits": [
      "Four Emperors",
      "Animal Kingdom Pirates"
    ],
    "color": [
      "Blue",
      "Purple"
    ],
    "attribute": [
      "Strike"
    ],
    "rarity": 1,
    "life": 4,
    "counter": 0,
    "labels": [
      "Low Cost"
    ],
    "archetype": "Control"
  },
  {
    "id": "OP01-002",
    "name": "Trafalgar Law",
    "type": "Leader",
    "cost": 0,
    "power": 5000,
    "effect": "[Activate Main] Once Per Turn (2 DON!!): If you have 5 Characters, return 1 of your Characters to the owners hand. Then, play up to 1 Character with a cost of 5 or less from your hand that is a different color than the returned Character.",
    "traits": [
      "Supernovas",
      "Heart Pirates"
    ],
    "color": [
      "Red",
      "Green"
    ],
    "attribute": [
      "Slash"
    ],
    "rarity": 1,
    "life": 4,
    "counter": 0,
    "labels": [
      "Summon",
      "Low Cost"
    ],
    "archetype": "Combo"
  },
  {
    "id": "OP01-031",
    "name": "Kozuki Oden",
    "type": "Leader",
    "cost": 0,
    "power": 5000,
    "effect": "[Activate Main] Once Per Turn You can trash 1 Wano Country type card from your hand: Set up to 2 of your DON!! cards as active.",
    "traits": [
      "Wano Country",
      "Kozuki Family"
    ],
    "color": [
      "Green"
    ],
    "attribute": [
      "Slash"
    ],
    "rarity": 1,
    "life": 5,
    "counter": 0,
    "labels": [
      "Discard",
      "Restand Don",
      "Low Cost"
    ],
    "archetype": "Midrange"
  },
  {
    "id": "OP01-060",
    "name": "Donquixote Doflamingo",
    "type": "Leader",
    "cost": 0,
    "power": 5000,
    "effect": "DON!!x2 [When Attacking] (1 DON!!): Reveal the top card of your deck. If it is a The Seven Warlords of the Sea type Character with a cost of 4 or less, you may play it rested.",
    "traits": [
      "The Seven Warlords of the Sea",
      "Donquixote Pirates"
    ],
    "color": [
      "Blue"
    ],
    "attribute": [
      "Special"
    ],
    "rarity": 1,
    "life": 5,
    "counter": 0,
    "labels": [
      "Summon",
      "Low Cost"
    ],
    "archetype": "Aggro"
  },
  {
    "id": "OP01-091",
    "name": "King",
    "type": "Leader",
    "cost": 0,
    "power": 5000,
    "effect": "Your Turn If you have 10 DON!! cards on your field, give all of your opponents Characters -1000 power.",
    "traits": [
      "Animal Kingdom Pirates"
    ],
    "color": [
      "Purple"
    ],
    "attribute": [
      "Special"
    ],
    "rarity": 1,
    "life": 0,
    "counter": 0,
    "labels": [
      "Debuff Power",
      "Low Cost"
    ],
    "archetype": "Control"
  },
  {
    "id": "OP01-062",
    "name": "Crocodile",
    "type": "Leader",
    "cost": 0,
    "power": 5000,
    "effect": "DON!! x1 After you activate an Event, you may draw 1 card if you have 4 or less cards in your hand and havent drawn a card using this Leaders effect during this turn",
    "traits": [
      "The Seven Warlords of the Sea",
      "Baroque Works"
    ],
    "color": [
      "Blue",
      "Purple"
    ],
    "attribute": [
      "Special"
    ],
    "rarity": 1,
    "life": 4,
    "counter": 0,
    "labels": [
      "Draw",
      "Low Cost"
    ],
    "archetype": "Combo"
  },
  {
    "id": "ST01-001",
    "name": "Monkey D. Luffy",
    "type": "Leader",
    "cost": 0,
    "power": 5000,
    "effect": "[Activate Main]Once Per Turn Give this Leader or 1 of your Characters 1 rested DON!! card.",
    "traits": [
      "Supernovas",
      "Straw Hat Crew"
    ],
    "color": [
      "Red"
    ],
    "attribute": [
      "Strike"
    ],
    "rarity": 1,
    "life": 5,
    "counter": 0,
    "labels": [
      "Low Cost"
    ],
    "archetype": "Midrange"
  },
  {
    "id": "ST02-001",
    "name": "Eustass Captain Kid",
    "type": "Leader",
    "cost": 0,
    "power": 5000,
    "effect": "[Activate Main] [Once per Turn] (3 DON!!) You may trash a card from your hand: Switch this Leader to Active.",
    "traits": [
      "Supernovas",
      "Kid Pirates"
    ],
    "color": [
      "Green"
    ],
    "attribute": [
      "Special"
    ],
    "rarity": 1,
    "life": 5,
    "counter": 0,
    "labels": [
      "Discard",
      "Low Cost"
    ],
    "archetype": "Midrange"
  },
  {
    "id": "ST03-001",
    "name": "Crocodile",
    "type": "Leader",
    "cost": 0,
    "power": 5000,
    "effect": "[Activate Main] [Once per Turn] <Don!! -4>: Return up to one cost 5 or lower Character to its owners hand.",
    "traits": [
      "The Seven Warlords of the Sea",
      "Baroque Works"
    ],
    "color": [
      "Blue"
    ],
    "attribute": [
      "Special"
    ],
    "rarity": 1,
    "life": 5,
    "counter": 0,
    "labels": [
      "Don Minus",
      "Low Cost"
    ],
    "archetype": "Control"
  },
  {
    "id": "ST04-001",
    "name": "Kaido",
    "type": "Leader",
    "cost": 0,
    "power": 5000,
    "effect": "[Activate Main]Once Per Turn DON!! -7: Trash the top card of your opponents life.",
    "traits": [
      "Four Emperors",
      "Animal Kingdom Pirates"
    ],
    "color": [
      "Purple"
    ],
    "attribute": [
      "Strike"
    ],
    "rarity": 1,
    "life": 5,
    "counter": 0,
    "labels": [
      "Don Minus",
      "Low Cost"
    ],
    "archetype": "Control"
  },
  {
    "id": "ST05-001",
    "name": "Shanks",
    "type": "Leader",
    "cost": 0,
    "power": 5000,
    "effect": "[Activate Main] Once per turn DON!! -3: Your <FILM> type Characters gain +2000 Power during this turn.",
    "traits": [
      "FILM",
      "Four Emperors",
      "Red Haired Pirates"
    ],
    "color": [
      "Purple"
    ],
    "attribute": [
      "Slash"
    ],
    "rarity": 1,
    "life": 5,
    "counter": 0,
    "labels": [
      "Buff Power",
      "Don Minus",
      "Low Cost"
    ],
    "archetype": "Midrange"
  },
  {
    "id": "OP02-049",
    "name": "Emporio Ivankov",
    "type": "Leader",
    "cost": 0,
    "power": 5000,
    "effect": "[End of Your Turn] If you have 0 cards in your hand, draw 2 cards.",
    "traits": [
      "Impel Down",
      "Revolutionary Army"
    ],
    "color": [
      "Blue"
    ],
    "attribute": [
      "Special"
    ],
    "rarity": 1,
    "life": 5,
    "counter": 0,
    "labels": [
      "Draw",
      "Low Cost"
    ],
    "archetype": "Combo"
  },
  {
    "id": "OP02-071",
    "name": "Magellan",
    "type": "Leader",
    "cost": 0,
    "power": 5000,
    "effect": "Your Turn [Once per Turn] When a DON!! card is returned from the field to the DON!! deck, this Leader gains +1000 Power during this turn.",
    "traits": [
      "Impel Down"
    ],
    "color": [
      "Purple"
    ],
    "attribute": [
      "Special"
    ],
    "rarity": 1,
    "life": 5,
    "counter": 0,
    "labels": [
      "Buff Power",
      "Low Cost"
    ],
    "archetype": "Midrange"
  },
  {
    "id": "OP02-093",
    "name": "Smoker",
    "type": "Leader",
    "cost": 0,
    "power": 5000,
    "effect": "DON!!x1 [Activate Main] Once Per Turn Give up to 1 of your opponents Characters -1 to their cost during this turn. Then, if there is a Character with a cost of 0, this Leader gains +1000 Power during this turn.",
    "traits": [
      "Navy"
    ],
    "color": [
      "Black"
    ],
    "attribute": [
      "Special"
    ],
    "rarity": 1,
    "life": 5,
    "counter": 0,
    "labels": [
      "Buff Power",
      "Low Cost"
    ],
    "archetype": "Control"
  },
  {
    "id": "OP02-025",
    "name": "Kin'emon",
    "type": "Leader",
    "cost": 0,
    "power": 5000,
    "effect": "[Activate Main] Once per turn When you have 1 or less Characters in play, reduce the play cost of the next cost 3 or higher Wano Country type Character card you play from your hand by 1 during this turn.",
    "traits": [
      "Wano Country",
      "Nine Red Scabbards"
    ],
    "color": [
      "Green"
    ],
    "attribute": [
      "Slash"
    ],
    "rarity": 1,
    "life": 5,
    "counter": 0,
    "labels": [
      "Summon",
      "Low Cost"
    ],
    "archetype": "Aggro"
  },
  {
    "id": "OP02-001",
    "name": "Edward Newgate",
    "type": "Leader",
    "cost": 0,
    "power": 6000,
    "effect": "[End of Your Turn] Add 1 card from the top of your Life Area to your hand.",
    "traits": [
      "The Four Emperors",
      "Whitebeard Pirates"
    ],
    "color": [
      "Red"
    ],
    "attribute": [
      "Special"
    ],
    "rarity": 1,
    "life": 6,
    "counter": 0,
    "labels": [
      "Low Cost"
    ],
    "archetype": "Midrange"
  },
  {
    "id": "OP02-072",
    "name": "Z",
    "type": "Leader",
    "cost": 0,
    "power": 5000,
    "effect": "[When Attacking] DON!!-4: KO one of your opponents Characters that costs 3 or less. Then, give this leader +1000 power during this turn.",
    "traits": [
      "FILM",
      "Neo Navy"
    ],
    "color": [
      "Purple",
      "Black"
    ],
    "attribute": [
      "Strike"
    ],
    "rarity": 1,
    "life": 4,
    "counter": 0,
    "labels": [
      "Removal",
      "Don Minus",
      "Low Cost"
    ],
    "archetype": "Control"
  },
  {
    "id": "OP02-002",
    "name": "Monkey D. Garp",
    "type": "Leader",
    "cost": 0,
    "power": 5000,
    "effect": "Your Turn When you attach DON!! to this Leader or your Characters, reduce by -1 the cost of up to 1 of your opponents cost 7 or lower Characters during this turn.",
    "traits": [
      "Navy"
    ],
    "color": [
      "Red",
      "Black"
    ],
    "attribute": [
      "Strike"
    ],
    "rarity": 1,
    "life": 4,
    "counter": 0,
    "labels": [
      "Low Cost"
    ],
    "archetype": "Control"
  },
  {
    "id": "OP02-026",
    "name": "Sanji",
    "type": "Leader",
    "cost": 0,
    "power": 5000,
    "effect": "Once Per Turn When you play a Character without an effect from your hand, if you have 3 or less Characters in play, set up to 2 of your Don!! to active.",
    "traits": [
      "Straw Hat Crew"
    ],
    "color": [
      "Green",
      "Blue"
    ],
    "attribute": [
      "Strike"
    ],
    "rarity": 1,
    "life": 4,
    "counter": 0,
    "labels": [
      "Summon",
      "Low Cost"
    ],
    "archetype": "Midrange"
  },
  {
    "id": "P-011",
    "name": "Uta",
    "type": "Leader",
    "cost": 0,
    "power": 5000,
    "effect": "[Activate Main] Once per turn (1 DON!!): Up to 1 of your Characters without effects gain +2000 Power during this turn.",
    "traits": [
      "FILM"
    ],
    "color": [
      "Red"
    ],
    "attribute": [
      "Special"
    ],
    "rarity": 1,
    "life": 0,
    "counter": 0,
    "labels": [
      "Buff Power",
      "Low Cost"
    ],
    "archetype": "Aggro"
  },
  {
    "id": "P-047",
    "name": "Monkey D Luffy",
    "type": "Leader",
    "cost": 0,
    "power": 5000,
    "effect": "DON!!x1 [When Attacking] If you have 3 or less cards in your hand, draw 1 card.",
    "traits": [
      "Straw Hat Crew"
    ],
    "color": [
      "Blue"
    ],
    "attribute": [
      "Strike"
    ],
    "rarity": 7,
    "life": 5,
    "counter": 0,
    "labels": [
      "Draw",
      "Low Cost"
    ],
    "archetype": "Midrange"
  },
  {
    "id": "P-076",
    "name": "Sakazuki",
    "type": "Leader",
    "cost": 0,
    "power": 5000,
    "effect": "[Activate Main] Once Per Turn You may trash 1 Navy type card from your hand: Give up to 1 of your opponents Characters -1 cost during this turn.",
    "traits": [
      "Navy"
    ],
    "color": [
      "Black",
      "Blue"
    ],
    "attribute": [
      "Special"
    ],
    "rarity": 7,
    "life": 4,
    "counter": 0,
    "labels": [
      "Removal",
      "Discard",
      "Cost Reduction",
      "Low Cost"
    ],
    "archetype": "Control"
  },
  {
    "id": "ST06-001",
    "name": "Sakazuki",
    "type": "Leader",
    "cost": 0,
    "power": 5000,
    "effect": "[Activate Main] [Once per Turn] (3 DON!!) You may trash 1 card from your hand: KO up to 1 of your opponents characters that costs 0.",
    "traits": [
      "Navy"
    ],
    "color": [
      "Black"
    ],
    "attribute": [
      "Special"
    ],
    "rarity": 1,
    "life": 5,
    "counter": 0,
    "labels": [
      "Removal",
      "Discard",
      "Low Cost"
    ],
    "archetype": "Control"
  },
  {
    "id": "ST07-001",
    "name": "Charlotte Linlin",
    "type": "Leader",
    "cost": 0,
    "power": 5000,
    "effect": "[When Attacking] DON!! x2 You may add 1 card from the top or bottom of your Life area to your hand: If your life is at 2 or less, you may place up to 1 card from your hand a the top of your Life area.",
    "traits": [
      "The Four Emperors",
      "Big Mom Pirates"
    ],
    "color": [
      "Yellow"
    ],
    "attribute": [
      "Special"
    ],
    "rarity": 1,
    "life": 5,
    "counter": 0,
    "labels": [
      "Low Cost"
    ],
    "archetype": "Combo"
  },
  {
    "id": "OP03-099",
    "name": "Charlotte Katakuri",
    "type": "Leader",
    "cost": 0,
    "power": 5000,
    "effect": "DON!!x1 [When Attacking] Look at up to 1 Life card from the top of your or your opponents Life Area and put it either on the top or the bottom of the Life Area. Then, this Leader gains +1000 Power for this battle.",
    "traits": [
      "Big Mom Pirates"
    ],
    "color": [
      "Yellow"
    ],
    "attribute": [
      "Strike"
    ],
    "rarity": 1,
    "life": 5,
    "counter": 0,
    "labels": [
      "Buff Power",
      "Rearrange Life",
      "Low Cost"
    ],
    "archetype": "Aggro"
  },
  {
    "id": "OP03-076",
    "name": "Rob Lucci",
    "type": "Leader",
    "cost": 0,
    "power": 5000,
    "effect": "Your Turn [Once per Turn] You may discard 2 cards from your hand: When an opponents Character is KOed, put this Leader to active.",
    "traits": [
      "CP9"
    ],
    "color": [
      "Black"
    ],
    "attribute": [
      "Strike"
    ],
    "rarity": 1,
    "life": 5,
    "counter": 0,
    "labels": [
      "Discard",
      "Low Cost"
    ],
    "archetype": "Control"
  },
  {
    "id": "OP03-022",
    "name": "Arlong",
    "type": "Leader",
    "cost": 0,
    "power": 5000,
    "effect": "DON!!x2 [When Attacking] (1 DON!!): Play up to 1 Character card with a cost of 4 or less with <Trigger> from your hand.",
    "traits": [
      "Fish-Man",
      "East Blue",
      "Arlong Crew"
    ],
    "color": [
      "Green",
      "Yellow"
    ],
    "attribute": [
      "Slash"
    ],
    "rarity": 1,
    "life": 4,
    "counter": 0,
    "labels": [
      "Summon",
      "Low Cost"
    ],
    "archetype": "Aggro"
  },
  {
    "id": "OP03-001",
    "name": "Portgas D. Ace",
    "type": "Leader",
    "cost": 0,
    "power": 5000,
    "effect": "When this Leader attacks or is being attacked, you may trash any number of Event or Stage cards from your hand. For each card you trashed, +1000 Power for this Leader during this battle.",
    "traits": [
      "Whitebeard Pirates"
    ],
    "color": [
      "Red"
    ],
    "attribute": [
      "Special"
    ],
    "rarity": 1,
    "life": 5,
    "counter": 0,
    "labels": [
      "Discard",
      "Low Cost"
    ],
    "archetype": "Combo"
  },
  {
    "id": "OP03-021",
    "name": "Kuro",
    "type": "Leader",
    "cost": 0,
    "power": 5000,
    "effect": "[Activate Main] (3 DON!!), you may rest 2 Characters with the East Blue type: Set this Leader to active and rest up to 1 of your opponents Characters that costs 5 or less.",
    "traits": [
      "East Blue",
      "Black Cat Pirates"
    ],
    "color": [
      "Green"
    ],
    "attribute": [
      "Slash"
    ],
    "rarity": 1,
    "life": 5,
    "counter": 0,
    "labels": [
      "Rest Character",
      "Low Cost"
    ],
    "archetype": "Combo"
  },
  {
    "id": "OP03-040",
    "name": "Nami",
    "type": "Leader",
    "cost": 0,
    "power": 5000,
    "effect": "As an additional rule, when your deck reaches 0 cards, you win the match instead of losing it. DON!!x1 When your opponent takes damage to their Life through the attack of this Leader, you may trash 1 card from the top of your deck.",
    "traits": [
      "East Blue"
    ],
    "color": [
      "Blue"
    ],
    "attribute": [
      "Wisdom"
    ],
    "rarity": 1,
    "life": 5,
    "counter": 0,
    "labels": [
      "Mill",
      "Low Cost"
    ],
    "archetype": "Combo"
  },
  {
    "id": "OP03-058",
    "name": "Iceburg",
    "type": "Leader",
    "cost": 0,
    "power": 5000,
    "effect": "This Leader can not attack. Acitvate:Main DON!!-1 You may rest this Leader: Play up to 1 Character with the Galley-La Company type that costs 5 or less from your hand.",
    "traits": [
      "Water Seven",
      "Galley-La Company"
    ],
    "color": [
      "Purple"
    ],
    "attribute": [
      "Wisdom"
    ],
    "rarity": 1,
    "life": 5,
    "counter": 0,
    "labels": [
      "Summon",
      "Don Minus",
      "Low Cost"
    ],
    "archetype": "Midrange"
  },
  {
    "id": "OP03-077",
    "name": "Charlotte Linlin",
    "type": "Leader",
    "cost": 0,
    "power": 5000,
    "effect": "DON!!x2 [When Attacking] (2 DON!!), you may trash 1 card from your hand: If you have 1 or fewer cards in your Life Area, put up to 1 card from the top of your deck on top of your Life Area.",
    "traits": [
      "The Four Emperors",
      "Big Mom Pirates"
    ],
    "color": [
      "Black",
      "Yellow"
    ],
    "attribute": [
      "Special"
    ],
    "rarity": 1,
    "life": 4,
    "counter": 0,
    "labels": [
      "Discard",
      "Mill",
      "Gain Life",
      "Low Cost"
    ],
    "archetype": "Control"
  },
  {
    "id": "ST08-001",
    "name": "Monkey D. Luffy",
    "type": "Leader",
    "cost": 0,
    "power": 5000,
    "effect": "Your Turn When a Character is KOd, give up to 1 rested DON!! to this Leader.",
    "traits": [
      "Straw Hat Crew"
    ],
    "color": [
      "Black"
    ],
    "attribute": [
      "Strike"
    ],
    "rarity": 1,
    "life": 5,
    "counter": 0,
    "labels": [
      "Low Cost"
    ],
    "archetype": "Control"
  },
  {
    "id": "ST09-001",
    "name": "Yamato",
    "type": "Leader",
    "cost": 0,
    "power": 5000,
    "effect": "DON!! x1[Opponents Turn] While your Life area has 2 cards or less, this Leader gains +1000 power.",
    "traits": [
      "Land of Wano"
    ],
    "color": [
      "Yellow"
    ],
    "attribute": [
      "Strike"
    ],
    "rarity": 1,
    "life": 5,
    "counter": 0,
    "labels": [
      "Buff Power",
      "Low Cost"
    ],
    "archetype": "Midrange"
  },
  {
    "id": "OP04-058",
    "name": "Crocodile",
    "type": "Leader",
    "cost": 0,
    "power": 5000,
    "effect": "[Opponents Turn] [Once per Turn] When you return DON!! from your field to the DON!! deck through one of your effects, add 1 DON!! from your DON!! deck as active.",
    "traits": [
      "The Seven Warlords of the Sea",
      "Baroque Works"
    ],
    "color": [
      "Purple",
      "Yellow"
    ],
    "attribute": [
      "Special"
    ],
    "rarity": 1,
    "life": 4,
    "counter": 0,
    "labels": [
      "Don Ramp",
      "Low Cost"
    ],
    "archetype": "Combo"
  },
  {
    "id": "OP04-001",
    "name": "Nefertari Vivi",
    "type": "Leader",
    "cost": 0,
    "power": 5000,
    "effect": "This Leader cannot attack. [Activate Main] [Once per Turn] (2 DON!!): Draw 1 card, and up to 1 of your Characters gains <Rush> during this turn.",
    "traits": [
      "Alabasta Kingdom"
    ],
    "color": [
      "Red",
      "Blue"
    ],
    "attribute": [
      "Slash"
    ],
    "rarity": 1,
    "life": 5,
    "counter": 0,
    "labels": [
      "Rush",
      "Draw",
      "Low Cost"
    ],
    "archetype": "Aggro"
  },
  {
    "id": "OP04-039",
    "name": "Rebecca",
    "type": "Leader",
    "cost": 0,
    "power": 5000,
    "effect": "This Leader cannot attack. [Activate Main] [Once per Turn] (1 DON!!): If you have 6 or less cards in your hand, look at 2 cards from the top of your deck; reveal up to 1 Dressrosa type card and add it to your hand. Then, trash the rest.",
    "traits": [
      "Dressrosa"
    ],
    "color": [
      "Black",
      "Blue"
    ],
    "attribute": [
      "Slash"
    ],
    "rarity": 1,
    "life": 5,
    "counter": 0,
    "labels": [
      "Low Cost"
    ],
    "archetype": "Control"
  },
  {
    "id": "OP04-019",
    "name": "Donquixote Doflamingo",
    "type": "Leader",
    "cost": 0,
    "power": 5000,
    "effect": "[End of Your Turn] Set up to 2 of your DON!! cards as active.",
    "traits": [
      "The Seven Warlords of the Sea",
      "Donquixote Pirates"
    ],
    "color": [
      "Purple",
      "Green"
    ],
    "attribute": [
      "Special"
    ],
    "rarity": 1,
    "life": 4,
    "counter": 0,
    "labels": [
      "Restand Don",
      "Low Cost"
    ],
    "archetype": "Control"
  },
  {
    "id": "OP04-020",
    "name": "Issho",
    "type": "Leader",
    "cost": 0,
    "power": 5000,
    "effect": "DON!! x1 Your Turn Give all of your opponents Characters -1 cost. [End of Your Turn] (1 DON!!): Set up to 1 of your Characters with a cost of 5 or less as active.",
    "traits": [
      "Navy"
    ],
    "color": [
      "Black",
      "Green"
    ],
    "attribute": [
      "Special"
    ],
    "rarity": 1,
    "life": 4,
    "counter": 0,
    "labels": [
      "Cost Reduction",
      "Low Cost"
    ],
    "archetype": "Control"
  },
  {
    "id": "OP04-040",
    "name": "Queen",
    "type": "Leader",
    "cost": 0,
    "power": 5000,
    "effect": "DON!! x1 [When Attacking] If the total number of cards in your Life and hand is 4 or less, draw 1 card. If you have a Character with a cost of 8 or more, you may place up to 1 card from the top of your deck on top of your Life instead of drawing 1 card.",
    "traits": [
      "Animal Kingdom Pirates"
    ],
    "color": [
      "Blue",
      "Yellow"
    ],
    "attribute": [
      "Ranged"
    ],
    "rarity": 1,
    "life": 4,
    "counter": 0,
    "labels": [
      "Draw",
      "Low Cost"
    ],
    "archetype": "Combo"
  },
  {
    "id": "ST10-001",
    "name": "Trafalgar Law",
    "type": "Leader",
    "cost": 0,
    "power": 5000,
    "effect": "[Activate Main] Once Per Turn DON!! -3: Place up to 1 of your opponents Characters with 3000 power or less at the bottom of the owners deck, and play up to 1 Character card with a cost of 4 or less from your hand.",
    "traits": [
      "Heart Pirates"
    ],
    "color": [
      "Red",
      "Purple"
    ],
    "attribute": [
      "Slash"
    ],
    "rarity": 1,
    "life": 4,
    "counter": 0,
    "labels": [
      "Summon",
      "Don Minus",
      "Low Cost"
    ],
    "archetype": "Aggro"
  },
  {
    "id": "ST10-002",
    "name": "Monkey D Luffy",
    "type": "Leader",
    "cost": 0,
    "power": 6000,
    "effect": "[Activate Main] Once Per Turn If you have 0 DON!! cards on your field or 8 or more DON!! cards on your field, add up to 1 DON!! card from your DON!! deck and set it as active.",
    "traits": [
      "Straw Hat Crew"
    ],
    "color": [
      "Red",
      "Purple"
    ],
    "attribute": [
      "Strike"
    ],
    "rarity": 1,
    "life": 3,
    "counter": 0,
    "labels": [
      "Low Cost"
    ],
    "archetype": "Aggro"
  },
  {
    "id": "ST10-003",
    "name": "EustassCaptainKid",
    "type": "Leader",
    "cost": 0,
    "power": 5000,
    "effect": "Your Turn If you have 4 or more Life cards, give this Leader -1000 power. [When Attacking] DON!! -1: This Leader gains +2000 power during this turn.",
    "traits": [
      "Kid Pirates"
    ],
    "color": [
      "Red",
      "Purple"
    ],
    "attribute": [
      "Special"
    ],
    "rarity": 1,
    "life": 5,
    "counter": 0,
    "labels": [
      "Buff Power",
      "Debuff Power",
      "Don Minus",
      "Low Cost"
    ],
    "archetype": "Combo"
  },
  {
    "id": "OP05-001",
    "name": "Sabo",
    "type": "Leader",
    "cost": 0,
    "power": 5000,
    "effect": "DON!! x1 [Opponents Turn] Once Per Turn If your Character with 5000 power or more would be KOd, you may give that Character -1000 power during this turn instead of that Character being KOd.",
    "traits": [
      "Revolutionary Army"
    ],
    "color": [
      "Red",
      "Black"
    ],
    "attribute": [
      "Special"
    ],
    "rarity": 1,
    "life": 4,
    "counter": 0,
    "labels": [
      "Debuff Power",
      "Protection",
      "Low Cost"
    ],
    "archetype": "Control"
  },
  {
    "id": "OP05-002",
    "name": "Belo Betty",
    "type": "Leader",
    "cost": 0,
    "power": 5000,
    "effect": "[Activate Main] Once Per Turn You may trash 1 Revolutionary Army type card from your hand: Up to 3 of your Revolutionary Army type Characters or Characters with a [Trigger] gain +3000 power during this turn.",
    "traits": [
      "Revolutionary Army"
    ],
    "color": [
      "Red",
      "Yellow"
    ],
    "attribute": [
      "Special"
    ],
    "rarity": 1,
    "life": 4,
    "counter": 0,
    "labels": [
      "Trigger",
      "Buff Power",
      "Discard",
      "Low Cost"
    ],
    "archetype": "Aggro"
  },
  {
    "id": "OP05-022",
    "name": "Donquixote Rosinante",
    "type": "Leader",
    "cost": 0,
    "power": 5000,
    "effect": "<Blocker> [End of Your Turn] If you have 6 or less cards in your hand, set this Leader as active.",
    "traits": [
      "Navy",
      "Donquixote Pirates"
    ],
    "color": [
      "Blue",
      "Green"
    ],
    "attribute": [
      "Special"
    ],
    "rarity": 1,
    "life": 4,
    "counter": 0,
    "labels": [
      "Blocker",
      "Low Cost"
    ],
    "archetype": "Combo"
  },
  {
    "id": "OP05-041",
    "name": "Sakazuki",
    "type": "Leader",
    "cost": 0,
    "power": 5000,
    "effect": "[Activate Main] Once Per Turn You may trash 1 card from your hand: Draw 1 card. [When Attacking] Give up to 1 of your opponents Characters -1 cost during this turn.",
    "traits": [
      "Navy"
    ],
    "color": [
      "Black",
      "Blue"
    ],
    "attribute": [
      "Special"
    ],
    "rarity": 1,
    "life": 4,
    "counter": 0,
    "labels": [
      "Removal",
      "Draw",
      "Discard",
      "Cost Reduction",
      "Low Cost"
    ],
    "archetype": "Control"
  },
  {
    "id": "OP05-060",
    "name": "Monkey.D.Luffy",
    "type": "Leader",
    "cost": 0,
    "power": 5000,
    "effect": "[Activate Main] Once Per Turn You may add 1 card from the top of your Life cards to your hand: If you have 0 or 3 or more DON!! cards on your field, add up to 1 DON!! card from your DON!! deck and set it as active.",
    "traits": [
      "Straw Hat Crew"
    ],
    "color": [
      "Purple"
    ],
    "attribute": [
      "Strike"
    ],
    "rarity": 1,
    "life": 5,
    "counter": 0,
    "labels": [
      "Low Cost"
    ],
    "archetype": "Midrange"
  },
  {
    "id": "OP05-098",
    "name": "Enel",
    "type": "Leader",
    "cost": 0,
    "power": 5000,
    "effect": "[Opponents Turn] Once Per Turn When your number of Life cards becomes 0, add 1 card from the top of your deck to the top of your Life cards. Then, trash 1 card from your hand.",
    "traits": [
      "Sky Island"
    ],
    "color": [
      "Yellow"
    ],
    "attribute": [
      "Special"
    ],
    "rarity": 1,
    "life": 4,
    "counter": 0,
    "labels": [
      "Discard",
      "Gain Life",
      "Low Cost"
    ],
    "archetype": "Combo"
  },
  {
    "id": "ST11-001",
    "name": "Uta",
    "type": "Leader",
    "cost": 0,
    "power": 5000,
    "effect": "DON!! x1 [When Attacking] Once Per Turn Reveal 1 card from the top of your deck and add up to 1 FILM type card to your hand. Then, place the rest at the bottom of your deck.",
    "traits": [
      "FILM"
    ],
    "color": [
      "Green"
    ],
    "attribute": [
      "Special"
    ],
    "rarity": 1,
    "life": 5,
    "counter": 0,
    "labels": [
      "Low Cost"
    ],
    "archetype": "Midrange"
  },
  {
    "id": "ST12-001",
    "name": "Roronoa Zoro & Sanji",
    "type": "Leader",
    "cost": 0,
    "power": 5000,
    "effect": "DON!! x1 [When Attacking] Once Per Turn You may return 1 of your Characters with a cost of 2 or more to the owners hand: Set up to 1 of your Characters with 7000 power or less as active.",
    "traits": [
      "Straw Hat Crew"
    ],
    "color": [
      "Blue",
      "Green"
    ],
    "attribute": [
      "Slash",
      "Strike"
    ],
    "rarity": 1,
    "life": 4,
    "counter": 0,
    "labels": [
      "Low Cost"
    ],
    "archetype": "Aggro"
  },
  {
    "id": "OP06-001",
    "name": "Uta",
    "type": "Leader",
    "cost": 0,
    "power": 5000,
    "effect": "[When Attacking] You may trash 1 FILM type card from your hand: Give up to 1 of your opponents characters -2000 power until the end of this turn. Then, add up to 1 DON!! from your DON!! deck as rested.",
    "traits": [
      "FILM"
    ],
    "color": [
      "Red",
      "Purple"
    ],
    "attribute": [
      "Special"
    ],
    "rarity": 1,
    "life": 0,
    "counter": 0,
    "labels": [
      "Removal",
      "Debuff Power",
      "Discard",
      "Don Ramp",
      "Low Cost"
    ],
    "archetype": "Combo"
  },
  {
    "id": "OP06-080",
    "name": "Gecko Moria",
    "type": "Leader",
    "cost": 0,
    "power": 5000,
    "effect": "DON!! x1 [When Attacking] (2 DON!!) You may discard 1 card from your hand: Trash the top 2 cards of your deck. Then play up to 1 Thriller Bark Pirates type Character card with a cost of 4 or less from your trash.",
    "traits": [
      "The Seven Warlords of the Sea",
      "Thriller Bark Pira"
    ],
    "color": [
      "Black"
    ],
    "attribute": [
      "Special"
    ],
    "rarity": 1,
    "life": 5,
    "counter": 0,
    "labels": [
      "Discard",
      "Mill",
      "Summon",
      "Trash Interaction",
      "Low Cost"
    ],
    "archetype": "Control"
  },
  {
    "id": "OP06-020",
    "name": "Hody Jones",
    "type": "Leader",
    "cost": 0,
    "power": 5000,
    "effect": "[Activate Main] You may rest this Leader: Rest up to 1 of your opponents DON!! cards or Characters with a cost of 3 or less. Then, you cannot add Life cards to your hand using your own effects during this turn.",
    "traits": [
      "Fish-Man",
      "New Fish-Man Pirates"
    ],
    "color": [
      "Green"
    ],
    "attribute": [
      "Strike"
    ],
    "rarity": 1,
    "life": 5,
    "counter": 0,
    "labels": [
      "Low Cost"
    ],
    "archetype": "Combo"
  },
  {
    "id": "OP06-021",
    "name": "Perona",
    "type": "Leader",
    "cost": 0,
    "power": 5000,
    "effect": "[Activate Main] Once Per Turn Choose one: \u00e2\u20ac\u00a2 Rest up to 1 of your opponents Characters with a cost of 4 or less. \u00e2\u20ac\u00a2 Give up to 1 of your opponents Characters -1 cost during this turn.",
    "traits": [
      "Thriller Bark Pirates"
    ],
    "color": [
      "Black",
      "Green"
    ],
    "attribute": [
      "Special"
    ],
    "rarity": 1,
    "life": 4,
    "counter": 0,
    "labels": [
      "Cost Reduction",
      "Rest Character",
      "Low Cost"
    ],
    "archetype": "Control"
  },
  {
    "id": "OP06-022",
    "name": "Yamato",
    "type": "Leader",
    "cost": 0,
    "power": 5000,
    "effect": "<Double Attack> [Activate Main] Once Per Turn If your opponent has 3 or less Life cards, give up to 2 rested DON!! cards to 1 of your Characters.",
    "traits": [
      "Land of Wano"
    ],
    "color": [
      "Green",
      "Yellow"
    ],
    "attribute": [
      "Strike"
    ],
    "rarity": 1,
    "life": 4,
    "counter": 0,
    "labels": [
      "Double Attack",
      "Low Cost"
    ],
    "archetype": "Aggro"
  },
  {
    "id": "OP06-042",
    "name": "Vinsmoke Reiju",
    "type": "Leader",
    "cost": 0,
    "power": 5000,
    "effect": "Your Turn Once Per Turn When a DON!! card on your field is returned to your DON!! deck, draw 1 card.",
    "traits": [
      "The Vinsmoke Family",
      "GERMA 66"
    ],
    "color": [
      "Blue",
      "Purple"
    ],
    "attribute": [
      "Special"
    ],
    "rarity": 1,
    "life": 4,
    "counter": 0,
    "labels": [
      "Draw",
      "Low Cost"
    ],
    "archetype": "Aggro"
  },
  {
    "id": "EB01-001",
    "name": "Kozuki Oden",
    "type": "Leader",
    "cost": 0,
    "power": 5000,
    "effect": "According to the rules, your character cards with the type Land of Wano without a counter have +1000 counter. DON!! X1 When attacking If you have a cost 5 or greater Land of Wano character in play, this leader gets +1000 power until the start of your next turn.",
    "traits": [
      "Land of Wano",
      "Kozuki Family"
    ],
    "color": [
      "Red",
      "Green"
    ],
    "attribute": [
      "Slash"
    ],
    "rarity": 1,
    "life": 4,
    "counter": 0,
    "labels": [
      "Low Cost"
    ],
    "archetype": "Combo"
  },
  {
    "id": "EB01-021",
    "name": "Hannyabal",
    "type": "Leader",
    "cost": 0,
    "power": 5000,
    "effect": "[End of Your Turn] You may return 1of your cost 2 or greater Impel Down Characters to your hand: Set up to one DON!! card from your DON!! deck as active.",
    "traits": [
      "Impel Down"
    ],
    "color": [
      "Blue",
      "Purple"
    ],
    "attribute": [
      "Slash"
    ],
    "rarity": 1,
    "life": 4,
    "counter": 0,
    "labels": [
      "Low Cost"
    ],
    "archetype": "Combo"
  },
  {
    "id": "EB01-040",
    "name": "Kyros",
    "type": "Leader",
    "cost": 1,
    "power": 5000,
    "effect": "[Activate Main] Once Per Turn You may turn the top card of your life face up: KO up to one of your opponents cost 0 characters.",
    "traits": [
      "Dressrosa"
    ],
    "color": [
      "Black",
      "Yellow"
    ],
    "attribute": [
      "Slash"
    ],
    "rarity": 1,
    "life": 4,
    "counter": 0,
    "labels": [
      "Low Cost"
    ],
    "archetype": "Control"
  },
  {
    "id": "OP07-001",
    "name": "Monkey.D.Dragon",
    "type": "Leader",
    "cost": 0,
    "power": 5000,
    "effect": "[Activate Main] Once Per Turn Give up to 2 total of your currently given DON!! cards to 1 of your Characters.",
    "traits": [
      "Revolutionary Army"
    ],
    "color": [
      "Red"
    ],
    "attribute": [
      "Special"
    ],
    "rarity": 1,
    "life": 5,
    "counter": 0,
    "labels": [
      "Low Cost"
    ],
    "archetype": "Aggro"
  },
  {
    "id": "OP07-019",
    "name": "Jewelry Bonney",
    "type": "Leader",
    "cost": 0,
    "power": 5000,
    "effect": "[On Your Opponents Attack] Once Per Turn (1 DON!!): Rest up to 1 of your opponents Leader or Character cards.",
    "traits": [
      "Supernovas",
      "Bonney Pirates"
    ],
    "color": [
      "Green"
    ],
    "attribute": [
      "Special"
    ],
    "rarity": 1,
    "life": 5,
    "counter": 0,
    "labels": [
      "Low Cost"
    ],
    "archetype": "Control"
  },
  {
    "id": "OP07-038",
    "name": "Boa Hancock",
    "type": "Leader",
    "cost": 0,
    "power": 5000,
    "effect": "Your Turn Once Per Turn This effect can be activated when a Character is removed from the field by your effect. If you have 5 or less cards in your hand, draw 1 card.",
    "traits": [
      "The Seven Warlords of the Sea",
      "Kuja Pirates"
    ],
    "color": [
      "Blue"
    ],
    "attribute": [
      "Special"
    ],
    "rarity": 1,
    "life": 5,
    "counter": 0,
    "labels": [
      "Draw",
      "Low Cost"
    ],
    "archetype": "Control"
  },
  {
    "id": "OP07-059",
    "name": "Foxy",
    "type": "Leader",
    "cost": 0,
    "power": 5000,
    "effect": "[When Attacking] DON!! -3: If you have 3 or more Foxy Pirates type Characters, select your opponents rested Leader and up to 1 Character card. The selected cards will not become active in your opponents next Refresh Phase.",
    "traits": [
      "Foxy Pirates"
    ],
    "color": [
      "Purple"
    ],
    "attribute": [
      "Special"
    ],
    "rarity": 1,
    "life": 5,
    "counter": 0,
    "labels": [
      "Don Minus",
      "Stun",
      "Low Cost"
    ],
    "archetype": "Combo"
  },
  {
    "id": "OP07-079",
    "name": "Rob Lucci",
    "type": "Leader",
    "cost": 0,
    "power": 5000,
    "effect": "[When Attacking] You may trash 2 cards from the top of your deck: Give up to 1 of your opponents Characters -1 cost during this turn.",
    "traits": [
      "CP0"
    ],
    "color": [
      "Black"
    ],
    "attribute": [
      "Strike"
    ],
    "rarity": 1,
    "life": 5,
    "counter": 0,
    "labels": [
      "Removal",
      "Mill",
      "Cost Reduction",
      "Low Cost"
    ],
    "archetype": "Control"
  },
  {
    "id": "OP07-097",
    "name": "Vegapunk",
    "type": "Leader",
    "cost": 0,
    "power": 5000,
    "effect": "This Leader cannot attack. [Activate Main] Once Per Turn \u00e2\u2018\u00a0: Select up to 1 Egghead type card with a cost of 5 or less from your hand and play it or add it to the top of your Life cards face-up.",
    "traits": [
      "Scientist",
      "Egghead"
    ],
    "color": [
      "Yellow"
    ],
    "attribute": [
      "Wisdom"
    ],
    "rarity": 1,
    "life": 2,
    "counter": 0,
    "labels": [
      "Gain Life",
      "Summon",
      "Low Cost"
    ],
    "archetype": "Combo"
  },
  {
    "id": "ST13-001",
    "name": "Sabo",
    "type": "Leader",
    "cost": 0,
    "power": 5000,
    "effect": "DON!! x1 [Activate Main] Once Per Turn You may add 1 of your Characters with a cost of 3 or more and 7000 power or more to the top of your Life cards face-up: Up to 1 of your Characters gains +2000 power until the start of your next turn.",
    "traits": [
      "Dressrosa",
      "Revolutionary Army"
    ],
    "color": [
      "Red",
      "Yellow"
    ],
    "attribute": [
      "Special"
    ],
    "rarity": 1,
    "life": 4,
    "counter": 0,
    "labels": [
      "Buff Power",
      "Gain Life",
      "Low Cost"
    ],
    "archetype": "Aggro"
  },
  {
    "id": "ST13-002",
    "name": "Portgas.D.Ace",
    "type": "Leader",
    "cost": 0,
    "power": 5000,
    "effect": "DON!! x2 [Activate Main] Once Per Turn Look at 5 cards from the top of your deck and add up to 1 Character card with a cost of 5 to the top of your Life cards face-up. Then, place the rest at the bottom of your deck in any order. [End of Your Turn] Trash all your face-up Life cards.",
    "traits": [
      "Whitebeard Pirates"
    ],
    "color": [
      "Blue",
      "Yellow"
    ],
    "attribute": [
      "Special"
    ],
    "rarity": 1,
    "life": 4,
    "counter": 0,
    "labels": [
      "Board Wipe",
      "Gain Life",
      "Rearrange Life",
      "Low Cost"
    ],
    "archetype": "Combo"
  },
  {
    "id": "ST13-003",
    "name": "Monkey.D.Luffy",
    "type": "Leader",
    "cost": 0,
    "power": 5000,
    "effect": "Your face-up Life cards are placed at the bottom of your deck instead of being added to your hand, according to the rules. DON!! x2 [Activate Main] Once Per Turn You may trash 1 card from your hand: If you have 0 Life cards, add up to 2 Character cards with a cost of 5 from your hand or trash to the top of your Life cards face-up.",
    "traits": [
      "Supernovas",
      "Straw Hat Crew"
    ],
    "color": [
      "Black",
      "Yellow"
    ],
    "attribute": [
      "Strike"
    ],
    "rarity": 1,
    "life": 4,
    "counter": 0,
    "labels": [
      "Discard",
      "Gain Life",
      "Low Cost"
    ],
    "archetype": "Combo"
  },
  {
    "id": "ST14-001",
    "name": "Monkey D. Luffy",
    "type": "Leader",
    "cost": 0,
    "power": 5000,
    "effect": "DON!! x1 All of your Characters gain +1 cost. If you have a Character with a cost of 8 or more, this Leader gains +1000 power.",
    "traits": [
      "Straw Hat Crew"
    ],
    "color": [
      "Black"
    ],
    "attribute": [
      "Strike"
    ],
    "rarity": 1,
    "life": 5,
    "counter": 0,
    "labels": [
      "Buff Power",
      "Increase Cost",
      "Low Cost"
    ],
    "archetype": "Control"
  },
  {
    "id": "OP08-001",
    "name": "Tony Tony.Chopper",
    "type": "Leader",
    "cost": 0,
    "power": 5000,
    "effect": "[Activate Main] Once Per Turn Give up to 3 of your Animal or Drum Kingdom type Characters up to 1 rested DON!! card each.",
    "traits": [
      "Animal",
      "Drum Kingdom",
      "Straw Hat Crew"
    ],
    "color": [
      "Red",
      "Green"
    ],
    "attribute": [
      "Strike"
    ],
    "rarity": 1,
    "life": 4,
    "counter": 0,
    "labels": [
      "Low Cost"
    ],
    "archetype": "Aggro"
  },
  {
    "id": "OP08-002",
    "name": "Marco",
    "type": "Leader",
    "cost": 0,
    "power": 5000,
    "effect": "DON!! x1 [Activate Main] Once Per Turn Draw 1 card and place 1 card from your hand at the top or bottom of your deck. Then, give up to 1 of your opponents Characters -2000 power during this turn.",
    "traits": [
      "Whitebeard Pirates"
    ],
    "color": [
      "Red",
      "Blue"
    ],
    "attribute": [
      "Special"
    ],
    "rarity": 1,
    "life": 4,
    "counter": 0,
    "labels": [
      "Debuff Power",
      "Draw",
      "Low Cost"
    ],
    "archetype": "Combo"
  },
  {
    "id": "OP08-021",
    "name": "Carrot",
    "type": "Leader",
    "cost": 0,
    "power": 5000,
    "effect": "[Activate Main] Once Per Turn If you have a Minks type Character, rest up to 1 of your opponents Characters with a cost of 5 or less.",
    "traits": [
      "Minks"
    ],
    "color": [
      "Green"
    ],
    "attribute": [
      "Special"
    ],
    "rarity": 1,
    "life": 5,
    "counter": 0,
    "labels": [
      "Rest Character",
      "Low Cost"
    ],
    "archetype": "Combo"
  },
  {
    "id": "OP08-057",
    "name": "King",
    "type": "Leader",
    "cost": 0,
    "power": 5000,
    "effect": "[Activate Main] Once Per Turn DON!! -2: Choose one: \u00e2\u20ac\u00a2 If you have 5 or less cards in your hand, draw 1 card. \u00e2\u20ac\u00a2 Give up to 1 of your opponents Characters -2 cost during this turn.",
    "traits": [
      "Animal Kingdom Pirates"
    ],
    "color": [
      "Purple",
      "Black"
    ],
    "attribute": [
      "Special"
    ],
    "rarity": 1,
    "life": 4,
    "counter": 0,
    "labels": [
      "Draw",
      "Cost Reduction",
      "Don Minus",
      "Low Cost"
    ],
    "archetype": "Control"
  },
  {
    "id": "OP08-058",
    "name": "Charlotte Pudding",
    "type": "Leader",
    "cost": 0,
    "power": 5000,
    "effect": "[When Attacking] You may turn 2 cards from the top of your Life cards face-up: Add up to 1 DON!! card from your DON!! deck and rest it.",
    "traits": [
      "Big Mom Pirates"
    ],
    "color": [
      "Purple",
      "Yellow"
    ],
    "attribute": [
      "Wisdom"
    ],
    "rarity": 1,
    "life": 4,
    "counter": 0,
    "labels": [
      "Low Cost"
    ],
    "archetype": "Combo"
  },
  {
    "id": "OP08-098",
    "name": "Kalgara",
    "type": "Leader",
    "cost": 0,
    "power": 5000,
    "effect": "DON!! x1 [When Attacking] Play up to 1 Shandian Warrior type Character card from your hand with a cost equal to or less than the number of DON!! cards on your field. If you do, add 1 card from the top of your Life cards to your hand.",
    "traits": [
      "Jaya",
      "Sky Island",
      "Shandian Warrior"
    ],
    "color": [
      "Yellow"
    ],
    "attribute": [
      "Slash"
    ],
    "rarity": 1,
    "life": 5,
    "counter": 0,
    "labels": [
      "Summon",
      "Low Cost"
    ],
    "archetype": "Midrange"
  }
]